python_gedcom_2/__init__.py
python_gedcom_2/element_creator.py
python_gedcom_2/helpers.py
python_gedcom_2/parser.py
python_gedcom_2/tags.py
python_gedcom_2/element/__init__.py
python_gedcom_2/element/adoption.py
python_gedcom_2/element/adult_christening.py
python_gedcom_2/element/annulment.py
python_gedcom_2/element/baptism.py
python_gedcom_2/element/bar_mitzvah.py
python_gedcom_2/element/bas_mitzvah.py
python_gedcom_2/element/birth.py
python_gedcom_2/element/blessing.py
python_gedcom_2/element/burial.py
python_gedcom_2/element/caste.py
python_gedcom_2/element/census.py
python_gedcom_2/element/children_count.py
python_gedcom_2/element/christening.py
python_gedcom_2/element/confirmation.py
python_gedcom_2/element/cremation.py
python_gedcom_2/element/date.py
python_gedcom_2/element/death.py
python_gedcom_2/element/divorce.py
python_gedcom_2/element/divorce_filed.py
python_gedcom_2/element/education.py
python_gedcom_2/element/element.py
python_gedcom_2/element/emigration.py
python_gedcom_2/element/engagement.py
python_gedcom_2/element/event.py
python_gedcom_2/element/event_detail.py
python_gedcom_2/element/family.py
python_gedcom_2/element/file.py
python_gedcom_2/element/first_communion.py
python_gedcom_2/element/graduation.py
python_gedcom_2/element/identification_number.py
python_gedcom_2/element/immigration.py
python_gedcom_2/element/individual.py
python_gedcom_2/element/marriage.py
python_gedcom_2/element/marriage_bann.py
python_gedcom_2/element/marriage_contract.py
python_gedcom_2/element/marriage_count.py
python_gedcom_2/element/marriage_license.py
python_gedcom_2/element/marriage_settlement.py
python_gedcom_2/element/nationality.py
python_gedcom_2/element/naturalization.py
python_gedcom_2/element/object.py
python_gedcom_2/element/occupation.py
python_gedcom_2/element/ordinance.py
python_gedcom_2/element/ordination.py
python_gedcom_2/element/physical_description.py
python_gedcom_2/element/probate.py
python_gedcom_2/element/property.py
python_gedcom_2-1.7.0.dist-info/LICENSE.txt
python_gedcom_2-1.7.0.dist-info/METADATA
python_gedcom_2-1.7.0.dist-info/WHEEL
python_gedcom_2-1.7.0.dist-info/top_level.txt
python_gedcom_2-1.7.0.dist-info/RECORD
