Metadata-Version: 2.1
Name: python-gedcom-2
Version: 1.7.0
Summary: A Python module for parsing, analyzing, and manipulating GEDCOM files.
Home-page: https://github.com/swanny0819/python-gedcom
Author: Patrick Swanson
Author-email: patswanson+python_gedcom@gmail.com
License: GPLv2
Project-URL: Bug Reports, https://github.com/swanny0819/python-gedcom/issues
Project-URL: Source, https://github.com/swanny0819/python-gedcom
Keywords: python gedcom parser
Platform: UNKNOWN
Classifier: Development Status :: 5 - Production/Stable
Classifier: Intended Audience :: Developers
Classifier: Topic :: Sociology :: Genealogy
Classifier: License :: OSI Approved :: GNU General Public License v2 (GPLv2)
Classifier: Programming Language :: Python :: 3
Classifier: Programming Language :: Python :: 3.5
Classifier: Programming Language :: Python :: 3.6
Classifier: Programming Language :: Python :: 3.7
Classifier: Programming Language :: Python :: 3.8
Classifier: Programming Language :: Python :: 3.9
License-File: LICENSE.txt
Provides-Extra: dev
Requires-Dist: setuptools ; extra == 'dev'
Requires-Dist: wheel ; extra == 'dev'
Requires-Dist: twine ; extra == 'dev'
Requires-Dist: pdoc3 ; extra == 'dev'
Provides-Extra: test
Requires-Dist: tox ; extra == 'test'
